{
  "1": {
    "id_s3": "reports/1/",
    "descricao": "Relatório de ocorrências registradas no sistema.",
    "deletado": false,
    "autor": "Leonardo Borges Silva Braga",
    "titulo": "Relatório de Ocorrências"
  },
  "2": {
    "id_s3": "reports/2/",
    "descricao": "Dados econômicos do Produto Interno Bruto (PIB).",
    "deletado": false,
    "autor": "Leonardo Borges Silva Braga",
    "titulo": "Relatório do PIB"
  },
  "3": {
    "id_s3": "reports/3/",
    "descricao": "Análise comparativa do PIB entre regiões.",
    "deletado": true,
    "autor": "Nulo",
    "titulo": "PIB Comparativo"
  },
  "4": {
    "id_s3": "reports/4/",
    "descricao": "Estatísticas sobre o ensino superior.",
    "deletado": false,
    "autor": "Marco Valerio",
    "titulo": "Ensino Superior no Brasil"
  }
}

